mps_client/__init__.py
mps_client/__main__.py
mps_client/_enums.py
mps_client/_exceptions.py
mps_client/cli/__init__.py
mps_client/cli/commands/__init__.py
mps_client/cli/commands/database.py
mps_client/cli/commands/download.py
mps_client/cli/commands/query.py
mps_client/cli/main.py
mps_client/cli/options.py
mps_client/cli/styles.py
mps_client/configuration.py
mps_client/core/__init__.py
mps_client/core/download.py
mps_client/core/graph_queries.py
mps_client/core/queries.py
mps_client/database/__init__.py
mps_client/database/connection.py
mps_client/database/graph.py
mps_client/database/session.py
mps_client/schema/__init__.py
mps_client/schema/base.py
mps_client/schema/esamp.py
mps_client/schema/jcap.py
mps_client/utils/__init__.py
mps_client/utils/log.py
mps_client/utils/sql.py
mps_client/utils/type_coercion.py
mps_client-0.3.1.dist-info/entry_points.txt
mps_client-0.3.1.dist-info/LICENSE
mps_client-0.3.1.dist-info/WHEEL
mps_client-0.3.1.dist-info/METADATA
mps_client-0.3.1.dist-info/RECORD
