Metadata-Version: 2.1
Name: mps-client
Version: 0.3.1
Summary: MPS Plotting and CLI Tool
License: Apache-2.0
Author: Michael Statt
Author-email: michael.statt@modelyst.io
Requires-Python: >=3.8.1,<4.0
Classifier: License :: OSI Approved :: Apache Software License
Classifier: Programming Language :: Python :: 3
Classifier: Programming Language :: Python :: 3.9
Classifier: Programming Language :: Python :: 3.10
Classifier: Programming Language :: Python :: 3.11
Requires-Dist: aiofiles (>=22.1.0,<23.0.0)
Requires-Dist: beautifulsoup4 (>=4.11.1,<5.0.0)
Requires-Dist: httpx (>=0.23.0,<0.24.0)
Requires-Dist: matplotlib (>=3.6.1,<4.0.0)
Requires-Dist: modelyst-dbgen (>=1.0.0a7,<2.0.0)
Requires-Dist: neo4j (>=5.3.0,<6.0.0)
Requires-Dist: pandas (>=1.5.1,<2.0.0)
Requires-Dist: requests (>=2.28.1,<3.0.0)
Requires-Dist: typer (>=0.6.1,<0.7.0)
